pymlb_statsapi/__init__.py
pymlb_statsapi/__version__.py
pymlb_statsapi/model/__init__.py
pymlb_statsapi/model/factory.py
pymlb_statsapi/model/registry.py
pymlb_statsapi/resources/__init__.py
pymlb_statsapi/resources/schemas/__init__.py
pymlb_statsapi/resources/schemas/endpoint-model.json
pymlb_statsapi/resources/schemas/statsapi/README.md
pymlb_statsapi/resources/schemas/statsapi/__init__.py
pymlb_statsapi/resources/schemas/statsapi/api_docs-1-0.json
pymlb_statsapi/resources/schemas/statsapi/stats_api_1_0/__init__.py
pymlb_statsapi/resources/schemas/statsapi/stats_api_1_0/awards.json
pymlb_statsapi/resources/schemas/statsapi/stats_api_1_0/broadcast.json
pymlb_statsapi/resources/schemas/statsapi/stats_api_1_0/conference.json
pymlb_statsapi/resources/schemas/statsapi/stats_api_1_0/config.json
pymlb_statsapi/resources/schemas/statsapi/stats_api_1_0/division.json
pymlb_statsapi/resources/schemas/statsapi/stats_api_1_0/draft.json
pymlb_statsapi/resources/schemas/statsapi/stats_api_1_0/game.json
pymlb_statsapi/resources/schemas/statsapi/stats_api_1_0/gamepace.json
pymlb_statsapi/resources/schemas/statsapi/stats_api_1_0/highlow.json
pymlb_statsapi/resources/schemas/statsapi/stats_api_1_0/homerunderby.json
pymlb_statsapi/resources/schemas/statsapi/stats_api_1_0/job.json
pymlb_statsapi/resources/schemas/statsapi/stats_api_1_0/league.json
pymlb_statsapi/resources/schemas/statsapi/stats_api_1_0/milestones.json
pymlb_statsapi/resources/schemas/statsapi/stats_api_1_0/person.json
pymlb_statsapi/resources/schemas/statsapi/stats_api_1_0/schedule.json
pymlb_statsapi/resources/schemas/statsapi/stats_api_1_0/season.json
pymlb_statsapi/resources/schemas/statsapi/stats_api_1_0/sports.json
pymlb_statsapi/resources/schemas/statsapi/stats_api_1_0/standings.json
pymlb_statsapi/resources/schemas/statsapi/stats_api_1_0/stats.json
pymlb_statsapi/resources/schemas/statsapi/stats_api_1_0/streaks.json
pymlb_statsapi/resources/schemas/statsapi/stats_api_1_0/team.json
pymlb_statsapi-1.4.3.dist-info/METADATA
pymlb_statsapi-1.4.3.dist-info/WHEEL
pymlb_statsapi-1.4.3.dist-info/licenses/LICENSE
pymlb_statsapi-1.4.3.dist-info/RECORD
