Metadata-Version: 2.4
Name: pymlb-statsapi
Version: 1.4.3
Summary: Python wrapper for MLB Stats API
Project-URL: Homepage, https://github.com/power-edge/pymlb_statsapi
Project-URL: Documentation, https://pymlb-statsapi.readthedocs.io/
Project-URL: Repository, https://github.com/power-edge/pymlb_statsapi
Project-URL: Issue Tracker, https://github.com/power-edge/pymlb_statsapi/issues
Project-URL: Changelog, https://github.com/power-edge/pymlb_statsapi/releases
Author-email: Nikolaus Schuetz <poweredgesports@gmail.com>
License-File: LICENSE
Requires-Python: >=3.10
Requires-Dist: requests>=2.32.2
Provides-Extra: dev
Requires-Dist: behave>=1.3.3; extra == 'dev'
Requires-Dist: hatch-vcs; extra == 'dev'
Requires-Dist: hatch>=1.15.1; extra == 'dev'
Requires-Dist: pre-commit>=4.3.0; extra == 'dev'
Requires-Dist: pytest>=8.4.2; extra == 'dev'
Requires-Dist: python-dotenv>=1.0.0; extra == 'dev'
Requires-Dist: ruff>=0.14.2; extra == 'dev'
Requires-Dist: twine>=6.2.0; extra == 'dev'
Provides-Extra: docs
Requires-Dist: myst-parser>=2.0.0; extra == 'docs'
Requires-Dist: sphinx-autodoc-typehints>=1.24.0; extra == 'docs'
Requires-Dist: sphinx-rtd-theme>=2.0.0; extra == 'docs'
Requires-Dist: sphinx>=7.0.0; extra == 'docs'
Provides-Extra: test
Requires-Dist: bandit>=1.7.0; extra == 'test'
Requires-Dist: behave>=1.2.6; extra == 'test'
Requires-Dist: pytest-cov>=4.1.0; extra == 'test'
Requires-Dist: pytest>=8.0.0; extra == 'test'
